[
  {
    "bank": "PRIVATBANK",
    "currency": "EUR",
    "buy": 40.35000,
    "sell": 41.35000,
    "rateDate": {
      "year": 2023,
      "month": 3,
      "dayOfMonth": 14,
      "hourOfDay": 15,
      "minute": 0,
      "second": 21
    }
  },
  {
    "bank": "PRIVATBANK",
    "currency": "USD",
    "buy": 37.20000,
    "sell": 37.70000,
    "rateDate": {
      "year": 2023,
      "month": 3,
      "dayOfMonth": 14,
      "hourOfDay": 15,
      "minute": 0,
      "second": 21
    }
  },
  {
    "bank": "NBU",
    "currency": "USD",
    "buy": 36.5686,
    "sell": 36.5686,
    "rateDate": {
      "year": 2023,
      "month": 3,
      "dayOfMonth": 14,
      "hourOfDay": 15,
      "minute": 0,
      "second": 22
    }
  },
  {
    "bank": "NBU",
    "currency": "EUR",
    "buy": 40.2639,
    "sell": 40.2639,
    "rateDate": {
      "year": 2023,
      "month": 3,
      "dayOfMonth": 14,
      "hourOfDay": 15,
      "minute": 0,
      "second": 22
    }
  },
  {
    "bank": "MONOBANK",
    "currency": "USD",
    "buy": 36.65,
    "sell": 37.4406,
    "rateDate": {
      "year": 2023,
      "month": 3,
      "dayOfMonth": 14,
      "hourOfDay": 15,
      "minute": 0,
      "second": 22
    }
  },
  {
    "bank": "MONOBANK",
    "currency": "EUR",
    "buy": 40.55,
    "sell": 41.6997,
    "rateDate": {
      "year": 2023,
      "month": 3,
      "dayOfMonth": 14,
      "hourOfDay": 15,
      "minute": 0,
      "second": 22
    }
  }
]